dataforest_pack/__init__.py
dataforest_pack/db_modules/__init__.py
dataforest_pack/db_modules/mongo_module.py
dataforest_pack-0.0.2.dist-info/LICENSE
dataforest_pack-0.0.2.dist-info/METADATA
dataforest_pack-0.0.2.dist-info/WHEEL
dataforest_pack-0.0.2.dist-info/top_level.txt
dataforest_pack-0.0.2.dist-info/RECORD
