Metadata-Version: 2.1
Name: dataforest-pack
Version: 0.0.2
Summary: Common modules and tool for being faster
Author: Serebrich Dmytro
Author-email: dmytro_s@dataforest.ai
License: UNKNOWN
Platform: UNKNOWN
Classifier: Programming Language :: Python :: 3
Classifier: License :: OSI Approved :: MIT License
Classifier: Operating System :: OS Independent
Requires-Python: >=3.6
License-File: LICENSE
